sillypass/__init__.py
sillypass/__main__.py
sillypass/sillypass.py
sillypass-1.0.0.dist-info/LICENSE
sillypass-1.0.0.dist-info/METADATA
sillypass-1.0.0.dist-info/WHEEL
sillypass-1.0.0.dist-info/entry_points.txt
sillypass-1.0.0.dist-info/top_level.txt
sillypass-1.0.0.dist-info/RECORD
