Metadata-Version: 2.1
Name: sillypass
Version: 1.0.0
Summary: Generate random passwords following silly rules like 1 letter, 1 number, 1 symbol
Home-page: https://gitlab.com/rjmorris/sillypass
Author: Joey Morris
License: MIT
Platform: UNKNOWN
Classifier: Development Status :: 4 - Beta
Classifier: Operating System :: OS Independent
Classifier: Intended Audience :: End Users/Desktop
Classifier: Topic :: Security
Classifier: Programming Language :: Python
Classifier: Programming Language :: Python :: 3
Classifier: Programming Language :: Python :: 3 :: Only
Classifier: Programming Language :: Python :: 3.6
Classifier: Programming Language :: Python :: 3.7
Classifier: Programming Language :: Python :: 3.8
Requires-Python: >= 3.6
